selventa_knowledge/__init__.py
selventa_knowledge/__main__.py
selventa_knowledge-1.1.2.dist-info/LICENSE
selventa_knowledge-1.1.2.dist-info/METADATA
selventa_knowledge-1.1.2.dist-info/WHEEL
selventa_knowledge-1.1.2.dist-info/entry_points.txt
selventa_knowledge-1.1.2.dist-info/top_level.txt
selventa_knowledge-1.1.2.dist-info/RECORD
