Metadata-Version: 2.1
Name: selventa-knowledge
Version: 1.1.2
Summary: Selventa Large and Small Corpora via PyBEL
Home-page: https://github.com/cthoyt/selventa-knowledge
Download-URL: https://github.com/cthoyt/selventa-knowledge/releases
Author: Charles Tapley Hoyt
Author-email: cthoyt@gmail.com
Maintainer: Charles Tapley Hoyt
Maintainer-email: cthoyt@gmail.com
License: MIT
Project-URL: Bug Tracker, https://github.com/cthoyt/selventa-knowledge/issues
Project-URL: Source Code, https://github.com/cthoyt/selventa-knowledge
Keywords: Biological Expression Language,BEL,Domain Specific Language,DSL,Systems biology,Networks biology,Drug repositioning
Classifier: Development Status :: 4 - Beta
Classifier: Environment :: Console
Classifier: Intended Audience :: Developers
Classifier: Intended Audience :: Science/Research
Classifier: Operating System :: OS Independent
Classifier: License :: OSI Approved :: MIT License
Classifier: Programming Language :: Python
Classifier: Programming Language :: Python :: 3.7
Classifier: Programming Language :: Python :: 3.6
Classifier: Programming Language :: Python :: 3 :: Only
Classifier: Topic :: Scientific/Engineering :: Bio-Informatics
Classifier: Topic :: Scientific/Engineering :: Chemistry
Requires-Python: >=3.6
License-File: LICENSE
Requires-Dist: pybel
